{
  "ID": "dee5eded-6472-4170-a4de-9a70c29d5d74",
  "Version": "2.2.8.0",
  "Name": "PlayScene",
  "Content": {
    "Content": {
      "Animation": {
        "Duration": 0,
        "Speed": 1.0,
        "Timelines": [],
        "ctype": "TimelineActionData"
      },
      "AnimationList": [],
      "ObjectData": {
        "Tag": 81,
        "Children": [
          {
            "FileData": {
              "Type": "Normal",
              "Path": "BackgroundLayer.json",
              "Plist": ""
            },
            "InnerActionSpeed": 1.0,
            "AnchorPoint": {},
            "Position": {
              "X": 0.0,
              "Y": 0.0
            },
            "Scale": {
              "ScaleX": 1.0,
              "ScaleY": 1.0
            },
            "CColor": {},
            "IconVisible": false,
            "PositionPercentXEnabled": true,
            "PositionPercentYEnabled": true,
            "PrePosition": {
              "X": 0.0,
              "Y": 0.0
            },
            "PreSize": {
              "X": 1.0,
              "Y": 1.0
            },
            "Tag": 82,
            "ActionTag": -615461194,
            "Size": {
              "X": 960.0,
              "Y": 640.0
            },
            "Name": "backgroundLayer",
            "ctype": "ProjectNodeObjectData"
          },
          {
            "FileData": {
              "Type": "Normal",
              "Path": "FruitLayer.json",
              "Plist": ""
            },
            "InnerActionSpeed": 1.0,
            "AnchorPoint": {},
            "Position": {
              "X": 0.0,
              "Y": 0.0
            },
            "Scale": {
              "ScaleX": 1.0,
              "ScaleY": 1.0
            },
            "CColor": {},
            "IconVisible": false,
            "PositionPercentXEnabled": true,
            "PositionPercentYEnabled": true,
            "PrePosition": {
              "X": 0.0,
              "Y": 0.0
            },
            "PreSize": {
              "X": 1.0,
              "Y": 1.0
            },
            "Tag": 85,
            "ActionTag": -1737993859,
            "Size": {
              "X": 960.0,
              "Y": 640.0
            },
            "Name": "fruitLayer",
            "ctype": "ProjectNodeObjectData"
          },
          {
            "FileData": {
              "Type": "Normal",
              "Path": "MenuLayer.json",
              "Plist": ""
            },
            "InnerActionSpeed": 1.0,
            "AnchorPoint": {},
            "Position": {
              "X": 0.0,
              "Y": 0.0
            },
            "Scale": {
              "ScaleX": 1.0,
              "ScaleY": 1.0
            },
            "CColor": {},
            "IconVisible": false,
            "PositionPercentXEnabled": true,
            "PositionPercentYEnabled": true,
            "PrePosition": {
              "X": 0.0,
              "Y": 0.0
            },
            "PreSize": {
              "X": 1.0,
              "Y": 1.0
            },
            "Tag": 97,
            "ActionTag": -163442745,
            "Size": {
              "X": 960.0,
              "Y": 640.0
            },
            "Name": "menuLayer",
            "ctype": "ProjectNodeObjectData"
          },
          {
            "FileData": {
              "Type": "Normal",
              "Path": "DialogLayer.json",
              "Plist": ""
            },
            "InnerActionSpeed": 1.0,
            "VisibleForFrame": false,
            "AnchorPoint": {},
            "Position": {
              "X": 0.0,
              "Y": 0.0
            },
            "Scale": {
              "ScaleX": 1.0,
              "ScaleY": 1.0
            },
            "CColor": {},
            "IconVisible": false,
            "PositionPercentXEnabled": true,
            "PositionPercentYEnabled": true,
            "PrePosition": {
              "X": 0.0,
              "Y": 0.0
            },
            "PreSize": {
              "X": 1.0,
              "Y": 1.0
            },
            "Tag": 194,
            "ActionTag": 182919484,
            "Size": {
              "X": 960.0,
              "Y": 640.0
            },
            "Name": "dialogLayer",
            "ctype": "ProjectNodeObjectData"
          }
        ],
        "Size": {
          "X": 960.0,
          "Y": 640.0
        },
        "Name": "Scene",
        "ctype": "SingleNodeObjectData"
      },
      "ctype": "GameProjectData"
    }
  },
  "Type": "Scene"
}